{
  "button": {
    "text": "Sign Up!"
  },
  "inputList": [
    {
      "name": "Email",
      "placeholder": "Choose your best email",
      "type": "email"
    },
    {
      "name": "Name",
      "placeholder": "Type your full name",
      "type": "name"
    },
    {
      "name": "Password",
      "placeholder": "Create a password",
      "type": "password"
    },
    {
      "name": "Confirm your password",
      "placeholder": "Repeat your created password",
      "type": "password"
    }
  ]
}
